{"commit_hash": "a6dbdf4b301a44c69a2852852d61431f0f80b023", "date": 1623942087000, "env_name": "virtualenv-py3.6-pip+casatasks-trunk-pip+casatools-trunk", "params": {"arch": "x86_64", "cpu": "Intel(R) Xeon(R) CPU E5-1660 v4 @ 3.20GHz", "machine": "NRAO workstation", "num_cpu": "16", "os": "Linux 3.10.0-1160.15.2.el7.x86_64", "ram": "32GB", "python": "3.6", "pip+casatools": "trunk", "pip+casatasks": "trunk"}, "python": "3.6", "requirements": {"pip+casatools": "trunk", "pip+casatasks": "trunk"}, "env_vars": {}, "result_columns": ["result", "params", "version", "started_at", "duration", "stats_ci_99_a", "stats_ci_99_b", "stats_q_25", "stats_q_75", "stats_number", "stats_repeat", "samples", "profile"], "results": {"casademo.calibration_suite.time_applycal_callib": [[49.42257120925933], [], "9ef394762fe7135f58c94c0e46a655fae93e7d107904ceff94d228f23b89a589", 1629912368229, null, [-250.98], [349.82], [46.419], [52.427], [2], [2]], "casademo.calibration_suite.time_bandpass": [[35.905411827145144], [], "f706aa044f6bc64b915996b7bdd6bc5666cae0eb7c47ff9a70b5bced6c9fbd0c", 1629912486216, null, [-483.93], [555.74], [30.707], [41.104], [2], [2]], "casademo.calibration_suite.time_gaincal": [[50.214745490578935], [], "56f8a9022caccdafe4240fb9a2766b2d5d56cc1c784bd724822d3b040f5b5309", 1629912564426, null, [32.866], [67.564], [50.041], [50.388], [2], [2]], "casademo.flagdata_suite.time_flagdata_bandpassflag": [[31.530172866303474], [], "f55e0ffa6be9d655555c5081a0e7bf2bc00b253273ba7c220de0bd2cfb3baf6c", 1629912689692, null, [31.289], [31.772], [31.528], [31.533], [2], [2]], "casademo.flagdata_suite.time_flagdata_list": [[135.39757494465448], [], "1a40b66ffb4a43d48af3407bae817ed4f7667fe778880859384f5f2e7c9c5d1f", 1629912752837, null, [133.78], [137.01], [135.38], [135.41], [2], [2]], "casademo.flagdata_suite.time_flagdata_list_summary": [[33.637091799639165], [], "3eb284062687484026a1defb4fceb705e83b244e37405f8794d431940ff44b08", 1629913023740, null, [15.285], [51.99], [33.454], [33.821], [2], [2]], "casademo.flagdata_suite.time_flagdata_summary": [[32.287273632129654], [], "9e569fb4e2a2f68e59c510bbf889632173be867104a4e5ba5a98d0eb110e82fb", 1629913090342, null, [31.071], [33.503], [32.275], [32.299], [2], [2]], "casademo.tclean_memory_suite.peakmem_tclean_setweighting": [[2154672128], [], "b08240b9d9211ba7e2ce323aae697e4b25deb8a6db4c5e2e48519cedc4707769", 1629913154940]}, "durations": {}, "version": 2}