{"results": {"casademo.flagdata_suite.time_flagdata_bandpassflag": {"result": [32.354424510966055], "stats": [{"ci_99": [30.52262780966703, 34.18622121226508], "q_25": 32.336106543953065, "q_75": 32.372742477979045, "min": 32.317788576940075, "max": 32.391060444992036, "mean": 32.354424510966055, "std": 0.03663593402598053, "repeat": 2, "number": 1}]}, "casademo.flagdata_suite.time_flagdata_list": {"result": [132.1813028405304], "stats": [{"ci_99": [86.83900281443493, 177.52360286662585], "q_25": 131.72787984026945, "q_75": 132.63472584079136, "min": 131.2744568400085, "max": 133.08814884105232, "mean": 132.1813028405304, "std": 0.9068460005219094, "repeat": 2, "number": 1}]}, "casademo.flagdata_suite.time_flagdata_list_summary": null, "casademo.flagdata_suite.time_flagdata_summary": {"result": [34.730029043974355], "stats": [{"ci_99": [30.142774341627955, 39.317283746320754], "q_25": 34.68415649695089, "q_75": 34.77590159099782, "min": 34.63828394992743, "max": 34.82177413802128, "mean": 34.730029043974355, "std": 0.09174509404692799, "repeat": 2, "number": 1}]}}, "params": {"arch": "x86_64", "cpu": "Intel(R) Xeon(R) CPU E5-1660 v4 @ 3.20GHz", "machine": "NRAO workstation", "num_cpu": "16", "os": "Linux 3.10.0-1160.15.2.el7.x86_64", "ram": "32GB", "python": "3.6"}, "requirements": {}, "commit_hash": "e605fc21706005b4c5dbf80cfb83da74e37a4ccb", "date": 1614785690000, "env_name": "virtualenv-py3.6", "python": "3.6", "profiles": {}, "started_at": {"casademo.flagdata_suite.time_flagdata_bandpassflag": 1626125948171, "casademo.flagdata_suite.time_flagdata_list": 1626126013168, "casademo.flagdata_suite.time_flagdata_list_summary": 1626125878460, "casademo.flagdata_suite.time_flagdata_summary": 1626126276195}, "ended_at": {"casademo.flagdata_suite.time_flagdata_bandpassflag": 1626126013167, "casademo.flagdata_suite.time_flagdata_list": 1626126276194, "casademo.flagdata_suite.time_flagdata_list_summary": 1626125878514, "casademo.flagdata_suite.time_flagdata_summary": 1626126345603}, "benchmark_version": {"casademo.flagdata_suite.time_flagdata_bandpassflag": "824484065f80daecec4d252656e0318d111b6349cf44f5302a66fbbf3544837e", "casademo.flagdata_suite.time_flagdata_list": "9e1ade09c980235f21b30562b68125f61596ef816e958b2005971bb9abf459e9", "casademo.flagdata_suite.time_flagdata_list_summary": "27804bea3d9405a9833b0b53254c6e5795764cdc018ae8e5e49410e017f654c6", "casademo.flagdata_suite.time_flagdata_summary": "c1463724171bf1f01a53834a5e05670c75b16d22946511a9e8fdccf05687f71b"}, "version": 1}